tathum/__init__.py
tathum/coord.py
tathum/functions.py
tathum/trajectory.py
tathum/trajectory_2d.py
tathum/trajectory_base.py
tathum/trajectory_mean.py
tathum-1.0.3.dist-info/LICENSE
tathum-1.0.3.dist-info/METADATA
tathum-1.0.3.dist-info/WHEEL
tathum-1.0.3.dist-info/top_level.txt
tathum-1.0.3.dist-info/RECORD
