Metadata-Version: 2.1
Name: tathum
Version: 1.0.3
Summary: TAT-HUM: Trajectory Analysis Toolkit for Human Movement
Home-page: https://github.com/xywang01/TAT-HUM
Author: X. Michael Wang, Centre for Motor Control, University of Toronto, Faculty of Kinesiology and Physical Education
Author-email: michaelwxy.wang@utoronto.ca
License: MIT
Download-URL: https://github.com/xywang01/TAT-HUM/archive/refs/tags/1.0.3.tar.gz
Platform: UNKNOWN
License-File: LICENSE
Requires-Dist: typing
Requires-Dist: numpy
Requires-Dist: pandas
Requires-Dist: scipy
Requires-Dist: scikit-spatial
Requires-Dist: vg
Requires-Dist: pytransform3d
Requires-Dist: matplotlib
Requires-Dist: seaborn
Requires-Dist: jupyter
